{
	"name": "dataflow1",
	"properties": {
		"type": "MappingDataFlow",
		"typeProperties": {
			"sources": [
				{
					"dataset": {
						"referenceName": "CustomerDataset",
						"type": "DatasetReference"
					},
					"name": "Customers"
				}
			],
			"sinks": [
				{
					"dataset": {
						"referenceName": "AzureSqlDWTable1",
						"type": "DatasetReference"
					},
					"name": "CustomerSink"
				}
			],
			"transformations": [
				{
					"name": "Select1"
				},
				{
					"name": "SurrogateKey1"
				},
				{
					"name": "DerivedColumn1"
				}
			],
			"script": "\n\nsource(output(\n\t\tSourceSystemID as integer,\n\t\tGlobalOrderID as string,\n\t\tSourceSystemCustomerID as string,\n\t\tLastName as string,\n\t\tFirstName as string,\n\t\tAddressLine1 as string,\n\t\tAddressLine2 as string,\n\t\tCity as string,\n\t\tState as string,\n\t\tZipCode as string,\n\t\tPhoneNumber as string,\n\t\tCreatedDate as date,\n\t\tUpdatedDate as date\n\t),\n\tallowSchemaDrift: true,\n\tvalidateSchema: false) ~> Customers\nCustomers select(mapColumn(\n\t\tCustomerID = GlobalOrderID,\n\t\tLastName,\n\t\tFirstName,\n\t\tAddressLine1,\n\t\tAddressLine2,\n\t\tCity,\n\t\tState,\n\t\tZipCode,\n\t\tPhoneNumber,\n\t\tRecordStartDate = CreatedDate,\n\t\tRecordEndDate = UpdatedDate\n\t)) ~> Select1\nSelect1 keyGenerate(output(CustomerSK as long),\n\tstartAt: 1L) ~> SurrogateKey1\nSurrogateKey1 derive(ActiveFlag = 1) ~> DerivedColumn1\nDerivedColumn1 sink(input(\n\t\tCustomerSK as integer,\n\t\tCustomerID as any,\n\t\tLastName as string,\n\t\tFirstName as string,\n\t\tAddressLine1 as string,\n\t\tAddressLine2 as string,\n\t\tCity as string,\n\t\tState as string,\n\t\tZipCode as string,\n\t\tPhoneNumber as string,\n\t\tRecordStartDate as date,\n\t\tRecordEndDate as date,\n\t\tActiveFlag as boolean\n\t),\n\tallowSchemaDrift: true,\n\tvalidateSchema: false,\n\tformat: 'table',\n\tstaged: true,\n\tdeletable:false,\n\tinsertable:true,\n\tupdateable:false,\n\tupsertable:false,\n\tmapColumn(\n\t\tCustomerSK,\n\t\tCustomerID,\n\t\tLastName,\n\t\tFirstName,\n\t\tAddressLine1,\n\t\tAddressLine2,\n\t\tCity,\n\t\tState,\n\t\tZipCode,\n\t\tPhoneNumber,\n\t\tRecordStartDate,\n\t\tRecordEndDate,\n\t\tActiveFlag\n\t)) ~> CustomerSink"
		}
	}
}