{
	"$schema": "http://schema.management.azure.com/schemas/2015-01-01/deploymentTemplate.json#",
	"contentVersion": "1.0.0.0",
	"parameters": {
		"factoryName": {
			"type": "string",
			"metadata": "Data Factory Name",
			"defaultValue": "zhenzh-adf"
		},
		"ADLSGen2LinkedService_accountKey": {
			"type": "secureString",
			"metadata": "Secure string for 'accountKey' of 'ADLSGen2LinkedService'"
		},
		"CloudSalesLinkedService_connectionString": {
			"type": "secureString",
			"metadata": "Secure string for 'connectionString' of 'CloudSalesLinkedService'"
		},
		"CloudSalesStreamingLinkedService_connectionString": {
			"type": "secureString",
			"metadata": "Secure string for 'connectionString' of 'CloudSalesStreamingLinkedService'"
		},
		"CosmosDbLinkedService_connectionString": {
			"type": "secureString",
			"metadata": "Secure string for 'connectionString' of 'CosmosDbLinkedService'"
		},
		"FileServer1_password": {
			"type": "secureString",
			"metadata": "Secure string for 'password' of 'FileServer1'"
		},
		"ReportingDWLinkedService_connectionString": {
			"type": "secureString",
			"metadata": "Secure string for 'connectionString' of 'ReportingDWLinkedService'"
		},
		"SqlServerLinkedService_connectionString": {
			"type": "secureString",
			"metadata": "Secure string for 'connectionString' of 'SqlServerLinkedService'"
		},
		"MovieSinkDataset_properties_typeProperties_fileName": {
			"type": "string",
			"defaultValue": ""
		},
		"MovieSinkDataset_properties_typeProperties_folderPath": {
			"type": "string",
			"defaultValue": "raw"
		},
		"ADLSGen2LinkedService_properties_typeProperties_url": {
			"type": "string",
			"defaultValue": "https://zhenzhmdwstorage.dfs.core.windows.net"
		},
		"FileServer1_properties_typeProperties_host": {
			"type": "string",
			"defaultValue": "C:\\"
		},
		"FileServer1_properties_typeProperties_userId": {
			"type": "string",
			"defaultValue": "openhackadmin"
		},
		"FourthCoffeeSelfHostedIR_properties_typeProperties_linkedInfo_resourceId": {
			"type": "string",
			"defaultValue": "/subscriptions/e139b3f3-760f-4d78-8ea1-8c713669b878/resourcegroups/petsahack-rg/providers/Microsoft.DataFactory/factories/petsahavtory/integrationruntimes/integrationRuntime1"
		}
	},
	"variables": {
		"factoryId": "[concat('Microsoft.DataFactory/factories/', parameters('factoryName'))]"
	},
	"resources": [
		{
			"name": "[concat(parameters('factoryName'), '/CopyCloudSales')]",
			"type": "Microsoft.DataFactory/factories/pipelines",
			"apiVersion": "2018-06-01",
			"properties": {
				"activities": [
					{
						"name": "ForEach_CloudSales",
						"type": "ForEach",
						"dependsOn": [],
						"userProperties": [],
						"typeProperties": {
							"items": {
								"value": "@pipeline().parameters.cw_items",
								"type": "Expression"
							},
							"activities": [
								{
									"name": "Copy_CloudSales",
									"type": "Copy",
									"dependsOn": [],
									"policy": {
										"timeout": "7.00:00:00",
										"retry": 0,
										"retryIntervalInSeconds": 30,
										"secureOutput": false,
										"secureInput": false
									},
									"userProperties": [
										{
											"name": "Source",
											"value": "dbo.@{item().source.table}"
										},
										{
											"name": "Destination",
											"value": "raw//@{item().destination.fileName}"
										}
									],
									"typeProperties": {
										"source": {
											"type": "AzureSqlSource"
										},
										"sink": {
											"type": "ParquetSink",
											"storeSettings": {
												"type": "AzureBlobFSWriteSettings"
											}
										},
										"enableStaging": false
									},
									"inputs": [
										{
											"referenceName": "SourceDataset_CloudSales",
											"type": "DatasetReference",
											"parameters": {
												"cw_table": "@item().source.table"
											}
										}
									],
									"outputs": [
										{
											"referenceName": "DestinationDataset_CloudSales",
											"type": "DatasetReference",
											"parameters": {
												"cw_fileName": "@item().destination.fileName"
											}
										}
									]
								}
							]
						}
					}
				],
				"parameters": {
					"cw_items": {
						"type": "Array",
						"defaultValue": [
							{
								"source": {
									"table": "Addresses"
								},
								"destination": {
									"fileName": "dboAddresses.parquet"
								}
							},
							{
								"source": {
									"table": "Customers"
								},
								"destination": {
									"fileName": "dboCustomers.parquet"
								}
							},
							{
								"source": {
									"table": "OrderDetails"
								},
								"destination": {
									"fileName": "dboOrderDetails.parquet"
								}
							},
							{
								"source": {
									"table": "Orders"
								},
								"destination": {
									"fileName": "dboOrders.parquet"
								}
							}
						]
					}
				},
				"annotations": []
			},
			"dependsOn": [
				"[concat(variables('factoryId'), '/datasets/SourceDataset_CloudSales')]",
				"[concat(variables('factoryId'), '/datasets/DestinationDataset_CloudSales')]"
			]
		},
		{
			"name": "[concat(parameters('factoryName'), '/CopyCloudSalesStreaming')]",
			"type": "Microsoft.DataFactory/factories/pipelines",
			"apiVersion": "2018-06-01",
			"properties": {
				"activities": [
					{
						"name": "ForEach_CloudSalesStreaming",
						"type": "ForEach",
						"dependsOn": [],
						"userProperties": [],
						"typeProperties": {
							"items": {
								"value": "@pipeline().parameters.cw_items",
								"type": "Expression"
							},
							"activities": [
								{
									"name": "Copy_CloudSalesStreaming",
									"type": "Copy",
									"dependsOn": [],
									"policy": {
										"timeout": "7.00:00:00",
										"retry": 0,
										"retryIntervalInSeconds": 30,
										"secureOutput": false,
										"secureInput": false
									},
									"userProperties": [
										{
											"name": "Source",
											"value": "dbo.@{item().source.table}"
										},
										{
											"name": "Destination",
											"value": "raw//@{item().destination.fileName}"
										}
									],
									"typeProperties": {
										"source": {
											"type": "AzureSqlSource"
										},
										"sink": {
											"type": "ParquetSink",
											"storeSettings": {
												"type": "AzureBlobFSWriteSettings"
											}
										},
										"enableStaging": false
									},
									"inputs": [
										{
											"referenceName": "SourceDataset_CloudSalesStreaming",
											"type": "DatasetReference",
											"parameters": {
												"cw_table": "@item().source.table"
											}
										}
									],
									"outputs": [
										{
											"referenceName": "DestinationDataset_CloudSalesStreaming",
											"type": "DatasetReference",
											"parameters": {
												"cw_fileName": "@item().destination.fileName"
											}
										}
									]
								}
							]
						}
					}
				],
				"parameters": {
					"cw_items": {
						"type": "Array",
						"defaultValue": [
							{
								"source": {
									"table": "Addresses"
								},
								"destination": {
									"fileName": "dboAddresses.parquet"
								}
							},
							{
								"source": {
									"table": "Customers"
								},
								"destination": {
									"fileName": "dboCustomers.parquet"
								}
							},
							{
								"source": {
									"table": "Transactions"
								},
								"destination": {
									"fileName": "dboTransactions.parquet"
								}
							}
						]
					}
				},
				"annotations": []
			},
			"dependsOn": [
				"[concat(variables('factoryId'), '/datasets/SourceDataset_CloudSalesStreaming')]",
				"[concat(variables('factoryId'), '/datasets/DestinationDataset_CloudSalesStreaming')]"
			]
		},
		{
			"name": "[concat(parameters('factoryName'), '/CopyMovies')]",
			"type": "Microsoft.DataFactory/factories/pipelines",
			"apiVersion": "2018-06-01",
			"properties": {
				"activities": [
					{
						"name": "CopyMovies",
						"type": "Copy",
						"dependsOn": [],
						"policy": {
							"timeout": "7.00:00:00",
							"retry": 0,
							"retryIntervalInSeconds": 30,
							"secureOutput": false,
							"secureInput": false
						},
						"userProperties": [],
						"typeProperties": {
							"source": {
								"type": "DocumentDbCollectionSource",
								"nestingSeparator": "."
							},
							"sink": {
								"type": "AzureBlobFSSink"
							},
							"enableStaging": false
						},
						"inputs": [
							{
								"referenceName": "MovieDataset",
								"type": "DatasetReference",
								"parameters": {}
							}
						],
						"outputs": [
							{
								"referenceName": "MovieSinkDataset",
								"type": "DatasetReference",
								"parameters": {}
							}
						]
					}
				],
				"annotations": []
			},
			"dependsOn": [
				"[concat(variables('factoryId'), '/datasets/MovieDataset')]",
				"[concat(variables('factoryId'), '/datasets/MovieSinkDataset')]"
			]
		},
		{
			"name": "[concat(parameters('factoryName'), '/CopyPipeline_FourthCoffee')]",
			"type": "Microsoft.DataFactory/factories/pipelines",
			"apiVersion": "2018-06-01",
			"properties": {
				"activities": [
					{
						"name": "Copy_FourthCoffee",
						"type": "Copy",
						"dependsOn": [],
						"policy": {
							"timeout": "7.00:00:00",
							"retry": 0,
							"retryIntervalInSeconds": 30,
							"secureOutput": false,
							"secureInput": false
						},
						"userProperties": [
							{
								"name": "Source",
								"value": "Rentals/"
							},
							{
								"name": "Destination",
								"value": "raw/fourth_coffee/"
							}
						],
						"typeProperties": {
							"source": {
								"type": "BinarySource",
								"storeSettings": {
									"type": "FileServerReadSettings",
									"recursive": true,
									"wildcardFileName": "*.*"
								}
							},
							"sink": {
								"type": "BinarySink",
								"storeSettings": {
									"type": "AzureBlobFSWriteSettings"
								}
							},
							"enableStaging": false
						},
						"inputs": [
							{
								"referenceName": "SourceDataset_FourthCoffee",
								"type": "DatasetReference",
								"parameters": {}
							}
						],
						"outputs": [
							{
								"referenceName": "DestinationDataset_FourthCoffee",
								"type": "DatasetReference",
								"parameters": {}
							}
						]
					}
				],
				"annotations": []
			},
			"dependsOn": [
				"[concat(variables('factoryId'), '/datasets/SourceDataset_FourthCoffee')]",
				"[concat(variables('factoryId'), '/datasets/DestinationDataset_FourthCoffee')]"
			]
		},
		{
			"name": "[concat(parameters('factoryName'), '/CopyPipeline_VanArsdel')]",
			"type": "Microsoft.DataFactory/factories/pipelines",
			"apiVersion": "2018-06-01",
			"properties": {
				"activities": [
					{
						"name": "ForEach_lq2",
						"type": "ForEach",
						"dependsOn": [],
						"userProperties": [],
						"typeProperties": {
							"items": {
								"value": "@pipeline().parameters.cw_items",
								"type": "Expression"
							},
							"activities": [
								{
									"name": "Copy_lq2",
									"type": "Copy",
									"dependsOn": [],
									"policy": {
										"timeout": "7.00:00:00",
										"retry": 0,
										"retryIntervalInSeconds": 30,
										"secureOutput": false,
										"secureInput": false
									},
									"userProperties": [
										{
											"name": "Source",
											"value": "dbo.@{item().source.table}"
										},
										{
											"name": "Destination",
											"value": "raw/VanArsdelLtd/@{item().destination.fileName}"
										}
									],
									"typeProperties": {
										"source": {
											"type": "SqlServerSource"
										},
										"sink": {
											"type": "DelimitedTextSink",
											"storeSettings": {
												"type": "AzureBlobFSWriteSettings"
											},
											"formatSettings": {
												"type": "DelimitedTextWriteSettings",
												"quoteAllText": true,
												"fileExtension": ".txt"
											}
										},
										"enableStaging": false
									},
									"inputs": [
										{
											"referenceName": "SourceDataset_lq2",
											"type": "DatasetReference",
											"parameters": {
												"cw_table": "@item().source.table"
											}
										}
									],
									"outputs": [
										{
											"referenceName": "DestinationDataset_lq2",
											"type": "DatasetReference",
											"parameters": {
												"cw_fileName": "@item().destination.fileName"
											}
										}
									]
								}
							]
						}
					}
				],
				"parameters": {
					"cw_items": {
						"type": "Array",
						"defaultValue": [
							{
								"source": {
									"table": "Actors"
								},
								"destination": {
									"fileName": "dboActors.csv"
								}
							},
							{
								"source": {
									"table": "Customers"
								},
								"destination": {
									"fileName": "dboCustomers.csv"
								}
							},
							{
								"source": {
									"table": "MovieActors"
								},
								"destination": {
									"fileName": "dboMovieActors.csv"
								}
							},
							{
								"source": {
									"table": "Movies"
								},
								"destination": {
									"fileName": "dboMovies.csv"
								}
							},
							{
								"source": {
									"table": "OnlineMovieMappings"
								},
								"destination": {
									"fileName": "dboOnlineMovieMappings.csv"
								}
							},
							{
								"source": {
									"table": "Transactions"
								},
								"destination": {
									"fileName": "dboTransactions.csv"
								}
							}
						]
					}
				},
				"annotations": []
			},
			"dependsOn": [
				"[concat(variables('factoryId'), '/datasets/SourceDataset_lq2')]",
				"[concat(variables('factoryId'), '/datasets/DestinationDataset_lq2')]"
			]
		},
		{
			"name": "[concat(parameters('factoryName'), '/pipeline1')]",
			"type": "Microsoft.DataFactory/factories/pipelines",
			"apiVersion": "2018-06-01",
			"properties": {
				"activities": [
					{
						"name": "dataflow1",
						"type": "ExecuteDataFlow",
						"dependsOn": [],
						"policy": {
							"timeout": "7.00:00:00",
							"retry": 0,
							"retryIntervalInSeconds": 30,
							"secureOutput": false,
							"secureInput": false
						},
						"userProperties": [],
						"typeProperties": {
							"dataflow": {
								"referenceName": "dataflow1",
								"type": "DataFlowReference",
								"parameters": {},
								"datasetParameters": {
									"Customers": {},
									"CustomerSink": {}
								}
							},
							"staging": {
								"linkedService": {
									"referenceName": "ADLSGen2LinkedService",
									"type": "LinkedServiceReference"
								},
								"folderPath": "staging"
							}
						}
					}
				],
				"annotations": []
			},
			"dependsOn": [
				"[concat(variables('factoryId'), '/dataflows/dataflow1')]",
				"[concat(variables('factoryId'), '/linkedServices/ADLSGen2LinkedService')]"
			]
		},
		{
			"name": "[concat(parameters('factoryName'), '/AzureSqlDWTable1')]",
			"type": "Microsoft.DataFactory/factories/datasets",
			"apiVersion": "2018-06-01",
			"properties": {
				"linkedServiceName": {
					"referenceName": "ReportingDWLinkedService",
					"type": "LinkedServiceReference"
				},
				"annotations": [],
				"type": "AzureSqlDWTable",
				"schema": [
					{
						"name": "CustomerSK",
						"type": "int",
						"precision": 10
					},
					{
						"name": "CustomerID",
						"type": "uniqueidentifier"
					},
					{
						"name": "LastName",
						"type": "varchar"
					},
					{
						"name": "FirstName",
						"type": "varchar"
					},
					{
						"name": "AddressLine1",
						"type": "varchar"
					},
					{
						"name": "AddressLine2",
						"type": "varchar"
					},
					{
						"name": "City",
						"type": "varchar"
					},
					{
						"name": "State",
						"type": "char"
					},
					{
						"name": "ZipCode",
						"type": "char"
					},
					{
						"name": "PhoneNumber",
						"type": "char"
					},
					{
						"name": "RecordStartDate",
						"type": "date"
					},
					{
						"name": "RecordEndDate",
						"type": "date"
					},
					{
						"name": "ActiveFlag",
						"type": "bit"
					}
				],
				"typeProperties": {
					"schema": "dbo",
					"table": "DimCustomers"
				}
			},
			"dependsOn": [
				"[concat(variables('factoryId'), '/linkedServices/ReportingDWLinkedService')]"
			]
		},
		{
			"name": "[concat(parameters('factoryName'), '/CustomerDataset')]",
			"type": "Microsoft.DataFactory/factories/datasets",
			"apiVersion": "2018-06-01",
			"properties": {
				"linkedServiceName": {
					"referenceName": "ADLSGen2LinkedService",
					"type": "LinkedServiceReference"
				},
				"annotations": [],
				"type": "Parquet",
				"typeProperties": {
					"location": {
						"type": "AzureBlobFSLocation",
						"folderPath": "customers_curated.parquet",
						"fileSystem": "curated"
					},
					"compressionCodec": "snappy"
				},
				"schema": [
					{
						"name": "SourceSystemID",
						"type": "INT32"
					},
					{
						"name": "GlobalOrderID",
						"type": "UTF8"
					},
					{
						"name": "SourceSystemCustomerID",
						"type": "UTF8"
					},
					{
						"name": "LastName",
						"type": "UTF8"
					},
					{
						"name": "FirstName",
						"type": "UTF8"
					},
					{
						"name": "AddressLine1",
						"type": "UTF8"
					},
					{
						"name": "AddressLine2",
						"type": "UTF8"
					},
					{
						"name": "City",
						"type": "UTF8"
					},
					{
						"name": "State",
						"type": "UTF8"
					},
					{
						"name": "ZipCode",
						"type": "UTF8"
					},
					{
						"name": "PhoneNumber",
						"type": "UTF8"
					},
					{
						"name": "CreatedDate",
						"type": "DATE"
					},
					{
						"name": "UpdatedDate",
						"type": "DATE"
					}
				]
			},
			"dependsOn": [
				"[concat(variables('factoryId'), '/linkedServices/ADLSGen2LinkedService')]"
			]
		},
		{
			"name": "[concat(parameters('factoryName'), '/DestinationDataset_CloudSales')]",
			"type": "Microsoft.DataFactory/factories/datasets",
			"apiVersion": "2018-06-01",
			"properties": {
				"linkedServiceName": {
					"referenceName": "ADLSGen2LinkedService",
					"type": "LinkedServiceReference"
				},
				"parameters": {
					"cw_fileName": {
						"type": "String"
					}
				},
				"annotations": [],
				"type": "Parquet",
				"typeProperties": {
					"location": {
						"type": "AzureBlobFSLocation",
						"fileName": {
							"value": "@dataset().cw_fileName",
							"type": "Expression"
						},
						"folderPath": "sales",
						"fileSystem": "raw"
					},
					"compressionCodec": "snappy"
				},
				"schema": []
			},
			"dependsOn": [
				"[concat(variables('factoryId'), '/linkedServices/ADLSGen2LinkedService')]"
			]
		},
		{
			"name": "[concat(parameters('factoryName'), '/DestinationDataset_CloudSalesStreaming')]",
			"type": "Microsoft.DataFactory/factories/datasets",
			"apiVersion": "2018-06-01",
			"properties": {
				"linkedServiceName": {
					"referenceName": "ADLSGen2LinkedService",
					"type": "LinkedServiceReference"
				},
				"parameters": {
					"cw_fileName": {
						"type": "String"
					}
				},
				"annotations": [],
				"type": "Parquet",
				"typeProperties": {
					"location": {
						"type": "AzureBlobFSLocation",
						"fileName": {
							"value": "@dataset().cw_fileName",
							"type": "Expression"
						},
						"folderPath": "sales_streaming",
						"fileSystem": "raw"
					},
					"compressionCodec": "snappy"
				},
				"schema": []
			},
			"dependsOn": [
				"[concat(variables('factoryId'), '/linkedServices/ADLSGen2LinkedService')]"
			]
		},
		{
			"name": "[concat(parameters('factoryName'), '/DestinationDataset_FourthCoffee')]",
			"type": "Microsoft.DataFactory/factories/datasets",
			"apiVersion": "2018-06-01",
			"properties": {
				"linkedServiceName": {
					"referenceName": "ADLSGen2LinkedService",
					"type": "LinkedServiceReference"
				},
				"annotations": [],
				"type": "Binary",
				"typeProperties": {
					"location": {
						"type": "AzureBlobFSLocation",
						"folderPath": "fourth_coffee",
						"fileSystem": "raw"
					}
				},
				"schema": []
			},
			"dependsOn": [
				"[concat(variables('factoryId'), '/linkedServices/ADLSGen2LinkedService')]"
			]
		},
		{
			"name": "[concat(parameters('factoryName'), '/DestinationDataset_i8m')]",
			"type": "Microsoft.DataFactory/factories/datasets",
			"apiVersion": "2018-06-01",
			"properties": {
				"linkedServiceName": {
					"referenceName": "ADLSGen2LinkedService",
					"type": "LinkedServiceReference"
				},
				"annotations": [],
				"type": "DelimitedText",
				"typeProperties": {
					"location": {
						"type": "AzureBlobFSLocation",
						"folderPath": "fourth_coffee",
						"fileSystem": "raw"
					},
					"columnDelimiter": ",",
					"escapeChar": "\\",
					"firstRowAsHeader": false,
					"quoteChar": "\""
				},
				"schema": [
					{
						"type": "String"
					},
					{
						"type": "String"
					},
					{
						"type": "String"
					}
				]
			},
			"dependsOn": [
				"[concat(variables('factoryId'), '/linkedServices/ADLSGen2LinkedService')]"
			]
		},
		{
			"name": "[concat(parameters('factoryName'), '/DestinationDataset_lq2')]",
			"type": "Microsoft.DataFactory/factories/datasets",
			"apiVersion": "2018-06-01",
			"properties": {
				"linkedServiceName": {
					"referenceName": "ADLSGen2LinkedService",
					"type": "LinkedServiceReference"
				},
				"parameters": {
					"cw_fileName": {
						"type": "String"
					}
				},
				"annotations": [],
				"type": "DelimitedText",
				"typeProperties": {
					"location": {
						"type": "AzureBlobFSLocation",
						"fileName": {
							"value": "@dataset().cw_fileName",
							"type": "Expression"
						},
						"folderPath": "VanArsdelLtd",
						"fileSystem": "raw"
					},
					"columnDelimiter": ",",
					"escapeChar": "\\",
					"firstRowAsHeader": false,
					"quoteChar": "\""
				},
				"schema": []
			},
			"dependsOn": [
				"[concat(variables('factoryId'), '/linkedServices/ADLSGen2LinkedService')]"
			]
		},
		{
			"name": "[concat(parameters('factoryName'), '/MovieDataset')]",
			"type": "Microsoft.DataFactory/factories/datasets",
			"apiVersion": "2018-06-01",
			"properties": {
				"linkedServiceName": {
					"referenceName": "CosmosDbLinkedService",
					"type": "LinkedServiceReference"
				},
				"annotations": [],
				"type": "DocumentDbCollection",
				"typeProperties": {
					"collectionName": "movies"
				}
			},
			"dependsOn": [
				"[concat(variables('factoryId'), '/linkedServices/CosmosDbLinkedService')]"
			]
		},
		{
			"name": "[concat(parameters('factoryName'), '/MovieSinkDataset')]",
			"type": "Microsoft.DataFactory/factories/datasets",
			"apiVersion": "2018-06-01",
			"properties": {
				"linkedServiceName": {
					"referenceName": "ADLSGen2LinkedService",
					"type": "LinkedServiceReference"
				},
				"annotations": [],
				"type": "AzureBlobFSFile",
				"typeProperties": {
					"format": {
						"type": "JsonFormat"
					},
					"fileName": "[parameters('MovieSinkDataset_properties_typeProperties_fileName')]",
					"folderPath": "[parameters('MovieSinkDataset_properties_typeProperties_folderPath')]"
				}
			},
			"dependsOn": [
				"[concat(variables('factoryId'), '/linkedServices/ADLSGen2LinkedService')]"
			]
		},
		{
			"name": "[concat(parameters('factoryName'), '/SourceDataset_CloudSales')]",
			"type": "Microsoft.DataFactory/factories/datasets",
			"apiVersion": "2018-06-01",
			"properties": {
				"linkedServiceName": {
					"referenceName": "CloudSalesLinkedService",
					"type": "LinkedServiceReference"
				},
				"parameters": {
					"cw_table": {
						"type": "String"
					}
				},
				"annotations": [],
				"type": "AzureSqlTable",
				"schema": [],
				"typeProperties": {
					"schema": "dbo",
					"table": {
						"value": "@dataset().cw_table",
						"type": "Expression"
					}
				}
			},
			"dependsOn": [
				"[concat(variables('factoryId'), '/linkedServices/CloudSalesLinkedService')]"
			]
		},
		{
			"name": "[concat(parameters('factoryName'), '/SourceDataset_CloudSalesStreaming')]",
			"type": "Microsoft.DataFactory/factories/datasets",
			"apiVersion": "2018-06-01",
			"properties": {
				"linkedServiceName": {
					"referenceName": "CloudSalesStreamingLinkedService",
					"type": "LinkedServiceReference"
				},
				"parameters": {
					"cw_table": {
						"type": "String"
					}
				},
				"annotations": [],
				"type": "AzureSqlTable",
				"schema": [],
				"typeProperties": {
					"schema": "dbo",
					"table": {
						"value": "@dataset().cw_table",
						"type": "Expression"
					}
				}
			},
			"dependsOn": [
				"[concat(variables('factoryId'), '/linkedServices/CloudSalesStreamingLinkedService')]"
			]
		},
		{
			"name": "[concat(parameters('factoryName'), '/SourceDataset_FourthCoffee')]",
			"type": "Microsoft.DataFactory/factories/datasets",
			"apiVersion": "2018-06-01",
			"properties": {
				"linkedServiceName": {
					"referenceName": "FileServer1",
					"type": "LinkedServiceReference"
				},
				"annotations": [],
				"type": "Binary",
				"typeProperties": {
					"location": {
						"type": "FileServerLocation",
						"folderPath": "Rentals"
					}
				},
				"schema": []
			},
			"dependsOn": [
				"[concat(variables('factoryId'), '/linkedServices/FileServer1')]"
			]
		},
		{
			"name": "[concat(parameters('factoryName'), '/SourceDataset_i8m')]",
			"type": "Microsoft.DataFactory/factories/datasets",
			"apiVersion": "2018-06-01",
			"properties": {
				"linkedServiceName": {
					"referenceName": "FileServer1",
					"type": "LinkedServiceReference"
				},
				"annotations": [],
				"type": "DelimitedText",
				"typeProperties": {
					"location": {
						"type": "FileServerLocation",
						"folderPath": "Rentals"
					},
					"columnDelimiter": ",",
					"escapeChar": "\\",
					"firstRowAsHeader": true,
					"quoteChar": "\""
				},
				"schema": [
					{
						"name": "ActorID",
						"type": "String"
					},
					{
						"name": "ActorName",
						"type": "String"
					},
					{
						"name": "Gender",
						"type": "String"
					}
				]
			},
			"dependsOn": [
				"[concat(variables('factoryId'), '/linkedServices/FileServer1')]"
			]
		},
		{
			"name": "[concat(parameters('factoryName'), '/SourceDataset_lq2')]",
			"type": "Microsoft.DataFactory/factories/datasets",
			"apiVersion": "2018-06-01",
			"properties": {
				"linkedServiceName": {
					"referenceName": "SqlServerLinkedService",
					"type": "LinkedServiceReference"
				},
				"parameters": {
					"cw_table": {
						"type": "String"
					}
				},
				"annotations": [],
				"type": "SqlServerTable",
				"schema": [],
				"typeProperties": {
					"schema": "dbo",
					"table": {
						"value": "@dataset().cw_table",
						"type": "Expression"
					}
				}
			},
			"dependsOn": [
				"[concat(variables('factoryId'), '/linkedServices/SqlServerLinkedService')]"
			]
		},
		{
			"name": "[concat(parameters('factoryName'), '/ADLSGen2LinkedService')]",
			"type": "Microsoft.DataFactory/factories/linkedServices",
			"apiVersion": "2018-06-01",
			"properties": {
				"annotations": [],
				"type": "AzureBlobFS",
				"typeProperties": {
					"url": "[parameters('ADLSGen2LinkedService_properties_typeProperties_url')]",
					"accountKey": {
						"type": "SecureString",
						"value": "[parameters('ADLSGen2LinkedService_accountKey')]"
					}
				}
			},
			"dependsOn": []
		},
		{
			"name": "[concat(parameters('factoryName'), '/CloudSalesLinkedService')]",
			"type": "Microsoft.DataFactory/factories/linkedServices",
			"apiVersion": "2018-06-01",
			"properties": {
				"annotations": [],
				"type": "AzureSqlDatabase",
				"typeProperties": {
					"connectionString": "[parameters('CloudSalesLinkedService_connectionString')]"
				}
			},
			"dependsOn": []
		},
		{
			"name": "[concat(parameters('factoryName'), '/CloudSalesStreamingLinkedService')]",
			"type": "Microsoft.DataFactory/factories/linkedServices",
			"apiVersion": "2018-06-01",
			"properties": {
				"annotations": [],
				"type": "AzureSqlDatabase",
				"typeProperties": {
					"connectionString": "[parameters('CloudSalesStreamingLinkedService_connectionString')]"
				}
			},
			"dependsOn": []
		},
		{
			"name": "[concat(parameters('factoryName'), '/CosmosDbLinkedService')]",
			"type": "Microsoft.DataFactory/factories/linkedServices",
			"apiVersion": "2018-06-01",
			"properties": {
				"annotations": [],
				"type": "CosmosDb",
				"typeProperties": {
					"connectionString": "[parameters('CosmosDbLinkedService_connectionString')]"
				}
			},
			"dependsOn": []
		},
		{
			"name": "[concat(parameters('factoryName'), '/FileServer1')]",
			"type": "Microsoft.DataFactory/factories/linkedServices",
			"apiVersion": "2018-06-01",
			"properties": {
				"annotations": [],
				"type": "FileServer",
				"typeProperties": {
					"host": "[parameters('FileServer1_properties_typeProperties_host')]",
					"userId": "[parameters('FileServer1_properties_typeProperties_userId')]",
					"password": {
						"type": "SecureString",
						"value": "[parameters('FileServer1_password')]"
					}
				},
				"connectVia": {
					"referenceName": "FourthCoffeeSelfHostedIR",
					"type": "IntegrationRuntimeReference"
				}
			},
			"dependsOn": [
				"[concat(variables('factoryId'), '/integrationRuntimes/FourthCoffeeSelfHostedIR')]"
			]
		},
		{
			"name": "[concat(parameters('factoryName'), '/ReportingDWLinkedService')]",
			"type": "Microsoft.DataFactory/factories/linkedServices",
			"apiVersion": "2018-06-01",
			"properties": {
				"annotations": [],
				"type": "AzureSqlDW",
				"typeProperties": {
					"connectionString": "[parameters('ReportingDWLinkedService_connectionString')]"
				}
			},
			"dependsOn": []
		},
		{
			"name": "[concat(parameters('factoryName'), '/SqlServerLinkedService')]",
			"type": "Microsoft.DataFactory/factories/linkedServices",
			"apiVersion": "2018-06-01",
			"properties": {
				"annotations": [],
				"type": "SqlServer",
				"typeProperties": {
					"connectionString": "[parameters('SqlServerLinkedService_connectionString')]"
				},
				"connectVia": {
					"referenceName": "FourthCoffeeSelfHostedIR",
					"type": "IntegrationRuntimeReference"
				}
			},
			"dependsOn": [
				"[concat(variables('factoryId'), '/integrationRuntimes/FourthCoffeeSelfHostedIR')]"
			]
		},
		{
			"name": "[concat(parameters('factoryName'), '/FourthCoffeeSelfHostedIR')]",
			"type": "Microsoft.DataFactory/factories/integrationRuntimes",
			"apiVersion": "2018-06-01",
			"properties": {
				"type": "SelfHosted",
				"typeProperties": {
					"linkedInfo": {
						"resourceId": "[parameters('FourthCoffeeSelfHostedIR_properties_typeProperties_linkedInfo_resourceId')]",
						"authorizationType": "Rbac"
					}
				}
			},
			"dependsOn": []
		},
		{
			"name": "[concat(parameters('factoryName'), '/dataflow1')]",
			"type": "Microsoft.DataFactory/factories/dataflows",
			"apiVersion": "2018-06-01",
			"properties": {
				"type": "MappingDataFlow",
				"typeProperties": {
					"sources": [
						{
							"dataset": {
								"referenceName": "CustomerDataset",
								"type": "DatasetReference"
							},
							"name": "Customers",
							"typeProperties": {}
						}
					],
					"sinks": [
						{
							"dataset": {
								"referenceName": "AzureSqlDWTable1",
								"type": "DatasetReference"
							},
							"name": "CustomerSink"
						}
					],
					"transformations": [
						{
							"name": "Select1"
						},
						{
							"name": "SurrogateKey1"
						},
						{
							"name": "DerivedColumn1"
						}
					],
					"script": "\n\nsource(output(\n\t\tSourceSystemID as integer,\n\t\tGlobalOrderID as string,\n\t\tSourceSystemCustomerID as string,\n\t\tLastName as string,\n\t\tFirstName as string,\n\t\tAddressLine1 as string,\n\t\tAddressLine2 as string,\n\t\tCity as string,\n\t\tState as string,\n\t\tZipCode as string,\n\t\tPhoneNumber as string,\n\t\tCreatedDate as date,\n\t\tUpdatedDate as date\n\t),\n\tallowSchemaDrift: true,\n\tvalidateSchema: false) ~> Customers\nCustomers select(mapColumn(\n\t\tCustomerID = GlobalOrderID,\n\t\tLastName,\n\t\tFirstName,\n\t\tAddressLine1,\n\t\tAddressLine2,\n\t\tCity,\n\t\tState,\n\t\tZipCode,\n\t\tPhoneNumber,\n\t\tRecordStartDate = CreatedDate,\n\t\tRecordEndDate = UpdatedDate\n\t)) ~> Select1\nSelect1 keyGenerate(output(CustomerSK as long),\n\tstartAt: 1L) ~> SurrogateKey1\nSurrogateKey1 derive(ActiveFlag = 1,\n\t\tCustomerID = toInteger(CustomerID)) ~> DerivedColumn1\nDerivedColumn1 sink(input(\n\t\tCustomerSK as integer,\n\t\tCustomerID as any,\n\t\tLastName as string,\n\t\tFirstName as string,\n\t\tAddressLine1 as string,\n\t\tAddressLine2 as string,\n\t\tCity as string,\n\t\tState as string,\n\t\tZipCode as string,\n\t\tPhoneNumber as string,\n\t\tRecordStartDate as date,\n\t\tRecordEndDate as date,\n\t\tActiveFlag as boolean\n\t),\n\tallowSchemaDrift: true,\n\tvalidateSchema: false,\n\tformat: 'table',\n\tstaged: true,\n\tdeletable:false,\n\tinsertable:true,\n\tupdateable:false,\n\tupsertable:false,\n\tmapColumn(\n\t\tCustomerSK,\n\t\tCustomerID,\n\t\tLastName,\n\t\tFirstName,\n\t\tAddressLine1,\n\t\tAddressLine2,\n\t\tCity,\n\t\tState,\n\t\tZipCode,\n\t\tPhoneNumber,\n\t\tRecordStartDate,\n\t\tRecordEndDate,\n\t\tActiveFlag\n\t)) ~> CustomerSink"
				}
			},
			"dependsOn": [
				"[concat(variables('factoryId'), '/datasets/AzureSqlDWTable1')]",
				"[concat(variables('factoryId'), '/datasets/CustomerDataset')]"
			]
		}
	]
}